pylurk/__init__.py
pylurk/conf.py
pylurk/cs.py
pylurk/debug.py
pylurk/lurk_client.py
pylurk/struct_lurk.py
pylurk/lurk/__init__.py
pylurk/lurk/lurk_lurk.py
pylurk/lurk/struct_lurk_lurk.py
pylurk/tls13/__init__.py
pylurk/tls13/crypto_suites.py
pylurk/tls13/key_scheduler.py
pylurk/tls13/lurk_tls13.py
pylurk/tls13/struct_lurk_tls13.py
pylurk/tls13/struct_tls13.py
pylurk/tls13/tls_handshake.py
pylurk-0.0.3.dist-info/LICENSE.txt
pylurk-0.0.3.dist-info/METADATA
pylurk-0.0.3.dist-info/WHEEL
pylurk-0.0.3.dist-info/top_level.txt
pylurk-0.0.3.dist-info/RECORD
