Metadata-Version: 2.1
Name: pylurk
Version: 0.0.3
Summary: "LURK"
Home-page: https://github.com/mglt/pylurk
Author: Daniel Migault
Author-email: mglt.biz@gmail.com
Project-URL: Bug Tracker, https://github.com/mglt/co2eq/issues
Classifier: Programming Language :: Python :: 3
Classifier: License :: OSI Approved :: MIT License
Classifier: Operating System :: OS Independent
Requires-Python: >=3.6
License-File: LICENSE.txt
